[{"inputs":[{"internalType":"contract IERC20","name":"_token","type":"address"},{"internalType":"address","name":"auctionAddress","type":"address"}],"stateMutability":"nonpayable","type":"constructor"},{"anonymous":false,"inputs":[{"indexed":true,"internalType":"address","name":"jobPoster","type":"address"},{"indexed":true,"internalType":"address","name":"workerNode","type":"address"},{"indexed":true,"internalType":"address","name":"validatorNode","type":"address"},{"indexed":false,"internalType":"string","name":"trainedModelMagnetLink","type":"string"},{"indexed":false,"internalType":"uint256","name":"id","type":"uint256"}],"name":"JobApproved","type":"event"},{"anonymous":false,"inputs":[{"indexed":false,"internalType":"address","name":"jobPoster","type":"address"},{"indexed":false,"internalType":"uint16","name":"estimatedTrainingTime","type":"uint16"},{"indexed":false,"internalType":"uint32","name":"trainingDatasetSize","type":"uint32"},{"indexed":false,"internalType":"address","name":"auctionAddress","type":"address"},{"indexed":false,"internalType":"uint256","name":"id","type":"uint256"},{"indexed":false,"internalType":"uint256","name":"workerReward","type":"uint256"},{"indexed":false,"internalType":"uint256","name":"biddingDeadline","type":"uint256"},{"indexed":false,"internalType":"uint256","name":"revealDeadline","type":"uint256"},{"indexed":false,"internalType":"uint64","name":"clientVersion","type":"uint64"}],"name":"JobDescriptionPosted","type":"event"},{"anonymous":false,"inputs":[{"indexed":true,"internalType":"address","name":"jobPoster","type":"address"},{"indexed":false,"internalType":"uint64","name":"targetErrorRate","type":"uint64"},{"indexed":true,"internalType":"uint256","name":"id","type":"uint256"},{"indexed":false,"internalType":"string","name":"trainedModelMagnetLink","type":"string"},{"indexed":false,"internalType":"string","name":"testingDatasetMagnetLink","type":"string"}],"name":"TestingDatasetShared","type":"event"},{"anonymous":false,"inputs":[{"indexed":true,"internalType":"address","name":"jobPoster","type":"address"},{"indexed":false,"internalType":"uint64","name":"trainingErrorRate","type":"uint64"},{"indexed":true,"internalType":"address","name":"workerNode","type":"address"},{"indexed":true,"internalType":"uint256","name":"id","type":"uint256"},{"indexed":false,"internalType":"string","name":"trainedModelMagnetLink","type":"string"}],"name":"TrainedModelShared","type":"event"},{"anonymous":false,"inputs":[{"indexed":true,"internalType":"address","name":"jobPoster","type":"address"},{"indexed":false,"internalType":"uint64","name":"targetErrorRate","type":"uint64"},{"indexed":true,"internalType":"address","name":"workerNode","type":"address"},{"indexed":true,"internalType":"uint256","name":"id","type":"uint256"},{"indexed":false,"internalType":"string","name":"untrainedModelMagnetLink","type":"string"},{"indexed":false,"internalType":"string","name":"trainingDatasetMagnetLink","type":"string"}],"name":"UntrainedModelAndTrainingDatasetShared","type":"event"},{"inputs":[{"internalType":"address","name":"_jobPoster","type":"address"},{"internalType":"uint256","name":"_id","type":"uint256"},{"internalType":"string","name":"_trainedModelMagnetLink","type":"string"}],"name":"approveJob","outputs":[],"stateMutability":"nonpayable","type":"function"},{"inputs":[{"internalType":"address","name":"","type":"address"},{"internalType":"uint256","name":"","type":"uint256"}],"name":"jobs","outputs":[{"internalType":"uint256","name":"auctionId","type":"uint256"},{"internalType":"address","name":"workerNode","type":"address"},{"internalType":"uint64","name":"targetErrorRate","type":"uint64"},{"internalType":"enum JobFactory.Status","name":"status","type":"uint8"},{"internalType":"uint64","name":"clientVersion","type":"uint64"}],"stateMutability":"view","type":"function"},{"inputs":[{"internalType":"uint16","name":"_estimatedTrainingTime","type":"uint16"},{"internalType":"uint32","name":"_trainingDatasetSize","type":"uint32"},{"internalType":"uint64","name":"_targetErrorRate","type":"uint64"},{"internalType":"uint256","name":"_minimumPayout","type":"uint256"},{"internalType":"uint256","name":"_workerReward","type":"uint256"},{"internalType":"uint64","name":"_clientVersion","type":"uint64"}],"name":"postJobDescription","outputs":[],"stateMutability":"nonpayable","type":"function"},{"inputs":[{"internalType":"uint256","name":"_id","type":"uint256"},{"internalType":"string","name":"_trainedModelMagnetLink","type":"string"},{"internalType":"string","name":"_testingDatasetMagnetLink","type":"string"}],"name":"shareTestingDataset","outputs":[],"stateMutability":"nonpayable","type":"function"},{"inputs":[{"internalType":"address","name":"_jobPoster","type":"address"},{"internalType":"uint256","name":"_id","type":"uint256"},{"internalType":"string","name":"_trainedModelMagnetLink","type":"string"},{"internalType":"uint64","name":"_trainingErrorRate","type":"uint64"}],"name":"shareTrainedModel","outputs":[],"stateMutability":"nonpayable","type":"function"},{"inputs":[{"internalType":"uint256","name":"_id","type":"uint256"},{"internalType":"string","name":"_untrainedModelMagnetLink","type":"string"},{"internalType":"string","name":"_trainingDatasetMagnetLink","type":"string"}],"name":"shareUntrainedModelAndTrainingDataset","outputs":[],"stateMutability":"nonpayable","type":"function"},{"inputs":[],"name":"token","outputs":[{"internalType":"contract IERC20","name":"","type":"address"}],"stateMutability":"view","type":"function"}]